{"expireTime":9007201008260760000,"key":"f9d10041f9ecb96226f63323bc1ae447","val":{"name":"IMAGE_PROCESSING","inputPaths":["/Users/snehamaheshwari/my-portfolio/content/featured/GlueIdentity/demo.png"],"outputDir":"/Users/snehamaheshwari/my-portfolio/public/static/c70a7afd5b45fc074ee8d24fe52253c0","args":{"isLazy":false,"operations":[{"outputPath":"ab668/demo.avif","args":{"height":119,"width":175,"cropFocus":17,"toFormat":"avif","fit":"cover"}},{"outputPath":"dfd3d/demo.avif","args":{"height":239,"width":350,"cropFocus":17,"toFormat":"avif","fit":"cover"}},{"outputPath":"f1f80/demo.avif","args":{"height":477,"width":700,"cropFocus":17,"toFormat":"avif","fit":"cover"}},{"outputPath":"1bc88/demo.avif","args":{"height":954,"width":1400,"cropFocus":17,"toFormat":"avif","fit":"cover"}}],"pluginOptions":{"base64Width":20,"forceBase64Format":"","useMozJpeg":false,"stripMetadata":true,"lazyImageGeneration":true,"defaultQuality":50,"failOnError":true,"plugins":[]}}}}